Metadata-Version: 2.1
Name: sanic-fire
Version: 0.1
Summary: sanic-fire is an extension for Sanic that adds support for commands to your application.
Home-page: https://github.com/tim2anna/sanic-fire
Author: Anna
Author-email: 
License: BSD License
Platform: all
Classifier: Environment :: Web Environment
Classifier: Intended Audience :: Developers
Classifier: License :: OSI Approved :: BSD License
Classifier: Operating System :: OS Independent
Classifier: Programming Language :: Python
Classifier: Topic :: Internet :: WWW/HTTP :: Dynamic Content
Classifier: Topic :: Software Development :: Libraries :: Python Modules
Classifier: Programming Language :: Python :: 3.7
Classifier: Programming Language :: Python :: 3.8
